Verilog/Day10_D_FlipFlop/d_flip_flop.v
module d_flip_flop (
    input  wire clk,
    input  wire reset,
    input  wire D,
    output reg  Q
);

always @(posedge clk or posedge reset) begin

    if (reset)
        Q <= 1'b0;

    else
        Q <= D;

end

endmodule

Verilog/Day10_D_FlipFlop/d_flip_flop_tb.v
`timescale 1ns/1ps

module d_flip_flop_tb;

reg clk;
reg reset;
reg D;

wire Q;

d_flip_flop uut (
    .clk(clk),
    .reset(reset),
    .D(D),
    .Q(Q)
);

// Clock generation: 10 ns period
always #5 clk = ~clk;

initial begin

    $dumpfile("dff.vcd");
    $dumpvars(0, d_flip_flop_tb);

    $monitor("Time=%0t Reset=%b D=%b Q=%b",
             $time, reset, D, Q);

    // Initial values
    clk = 0;
    reset = 1;
    D = 0;

    // Asynchronous reset
    #7;
    reset = 0;

    // D = 1, captured at next rising edge
    D = 1;
    #10;

    // D = 0, captured at next rising edge
    D = 0;
    #10;

    // D = 1 again
    D = 1;
    #10;

    // Test asynchronous reset again
    reset = 1;
    #3;
    reset = 0;

    #10;

    $finish;

end

endmodule

Verilog/Day10_D_FlipFlop/dff.vcd
$date
	Mon Jul 20 21:15:42 2026
$end
$version
	Icarus Verilog
$end
$timescale
	1ps
$end
$scope module d_flip_flop_tb $end
$var wire 1 ! Q $end
$var reg 1 " D $end
$var reg 1 # clk $end
$var reg 1 $ reset $end
$scope module uut $end
$var wire 1 " D $end
$var wire 1 # clk $end
$var wire 1 $ reset $end
$var reg 1 ! Q $end
$upscope $end
$upscope $end
$enddefinitions $end
$comment Show the parameter values. $end
$dumpall
$end
#0
$dumpvars
1$
0#
0"
0!
$end
#5000
1#
#7000
1"
0$
#10000
0#
#15000
1!
1#
#17000
0"
#20000
0#
#25000
0!
1#
#27000
1"
#30000
0#
#35000
1!
1#
#37000
0!
1$
#40000
0$
0#
#45000
1!
1#
